{
  "lastRun": "2026-02-22T21:27:28.004Z",
  "nextScheduledRun": "2026-02-23T21:00:00.000Z",
  "sources": [
    {
      "name": "gorunning",
      "status": "failed",
      "itemCount": 0,
      "lastUpdated": "2026-02-22T21:27:26.513Z",
      "error": "page.goto: Timeout 30000ms exceeded.\nCall log:\n  - navigating to \"https://gorunning.kr/races\", waiting until \"networkidle\"\n"
    },
    {
      "name": "aims",
      "status": "success",
      "itemCount": 355,
      "lastUpdated": "2026-02-22T21:27:27.928Z"
    }
  ],
  "totalEvents": 340,
  "krEvents": 4,
  "intlEvents": 336,
  "version": "1.0.0"
}