{
  "lastRun": "2026-02-10T21:43:45.468Z",
  "nextScheduledRun": "2026-02-11T21:00:00.000Z",
  "sources": [
    {
      "name": "gorunning",
      "status": "failed",
      "itemCount": 0,
      "lastUpdated": "2026-02-10T21:43:44.385Z",
      "error": "page.goto: Timeout 30000ms exceeded.\nCall log:\n  - navigating to \"https://gorunning.kr/races\", waiting until \"networkidle\"\n"
    },
    {
      "name": "aims",
      "status": "success",
      "itemCount": 356,
      "lastUpdated": "2026-02-10T21:43:45.393Z"
    }
  ],
  "totalEvents": 342,
  "krEvents": 4,
  "intlEvents": 338,
  "version": "1.0.0"
}